.DS_Store
myPackage/__init__.py
mypackagedodel/__init__.py
mypackagedodel-0.1.0.dist-info/METADATA
mypackagedodel-0.1.0.dist-info/WHEEL
mypackagedodel-0.1.0.dist-info/top_level.txt
mypackagedodel-0.1.0.dist-info/RECORD
