Metadata-Version: 2.1
Name: mypackagedodel
Version: 0.1.0
Summary: My Python package
Home-page: https://betterscientificsoftware.github.io/python-for-hpc/tutorials/python-pypi-packaging/#creating-a-python-package
Author: Danila Kuriabov
Author-email: testmail@mail.ru
License: BSD 2-clause
Platform: UNKNOWN
Classifier: Development Status :: 1 - Planning
Classifier: Intended Audience :: Science/Research
Classifier: License :: OSI Approved :: BSD License
Classifier: Operating System :: POSIX :: Linux
Classifier: Programming Language :: Python :: 2
Classifier: Programming Language :: Python :: 2.7
Classifier: Programming Language :: Python :: 3
Classifier: Programming Language :: Python :: 3.4
Classifier: Programming Language :: Python :: 3.5
Requires-Dist: numpy
Requires-Dist: topas2numpy
